{
  "$schema": "https://biomejs.dev/schemas/2.1.3/schema.json",
  "vcs": {
    "enabled": false,
    "clientKind": "git",
    "useIgnoreFile": true
  },
  "files": {
    "ignoreUnknown": false,
    "includes": ["**", "!**/dist/**/*", "!**/.vscode/**/*", "!**/*.css"]
  },
  "formatter": {
    "enabled": true,
    "useEditorconfig": true
  },
  "linter": {
    "enabled": true,
    "rules": {
      "recommended": true
    }
  },
  "assist": { "actions": { "source": { "organizeImports": "on" } } },
  "javascript": {
    "formatter": {
      "quoteStyle": "double"
    }
  }
}
